momake/__init__.py
momake/dependency.py
momake/exceptions.py
momake/finder.py
momake/runlog/__init__.py
momake/runlog/commands.py
momake/runlog/conn.py
momake/runlog/db.py
momake/runlog/queries.py
momake/runlog/tables.py
momake/runner.py
momake/task.py
momake-0.1.0.dist-info/METADATA
momake-0.1.0.dist-info/WHEEL
momake-0.1.0.dist-info/entry_points.txt
momake-0.1.0.dist-info/RECORD
