Metadata-Version: 2.3
Name: momake
Version: 0.1.0
Summary: 
Author: Dominik Dlugajczyk
Author-email: msocek@gmail.com
Requires-Python: >=3.13
Classifier: Programming Language :: Python :: 3
Classifier: Programming Language :: Python :: 3.13
Requires-Dist: click (>=8.1.8,<9.0.0)
Requires-Dist: sqlalchemy (>=2.0.40,<3.0.0)
